odoo/addons/ssi_accountant_general_audit_ws_ra120/README.rst
odoo/addons/ssi_accountant_general_audit_ws_ra120/__init__.py
odoo/addons/ssi_accountant_general_audit_ws_ra120/__manifest__.py
odoo/addons/ssi_accountant_general_audit_ws_ra120/data/accountant_general_audit_worksheet_type_data.xml
odoo/addons/ssi_accountant_general_audit_ws_ra120/data/approval_template_data.xml
odoo/addons/ssi_accountant_general_audit_ws_ra120/data/ir_sequence_data.xml
odoo/addons/ssi_accountant_general_audit_ws_ra120/data/policy_template_data.xml
odoo/addons/ssi_accountant_general_audit_ws_ra120/data/sequence_template_data.xml
odoo/addons/ssi_accountant_general_audit_ws_ra120/models/__init__.py
odoo/addons/ssi_accountant_general_audit_ws_ra120/models/accountant_balance_diff_category.py
odoo/addons/ssi_accountant_general_audit_ws_ra120/models/accountant_client_account_type.py
odoo/addons/ssi_accountant_general_audit_ws_ra120/models/ws_ra1201.py
odoo/addons/ssi_accountant_general_audit_ws_ra120/models/ws_ra1201_account_mapping.py
odoo/addons/ssi_accountant_general_audit_ws_ra120/models/ws_ra1202.py
odoo/addons/ssi_accountant_general_audit_ws_ra120/models/ws_ra1202_balance_diff.py
odoo/addons/ssi_accountant_general_audit_ws_ra120/models/ws_ra1203.py
odoo/addons/ssi_accountant_general_audit_ws_ra120/models/ws_ra1203_balance_diff.py
odoo/addons/ssi_accountant_general_audit_ws_ra120/models/ws_ra1204.py
odoo/addons/ssi_accountant_general_audit_ws_ra120/models/ws_ra1204_extrapolation_adjustment.py
odoo/addons/ssi_accountant_general_audit_ws_ra120/security/ir.model.access.csv
odoo/addons/ssi_accountant_general_audit_ws_ra120/security/ir_module_category_data.xml
odoo/addons/ssi_accountant_general_audit_ws_ra120/security/ir_rule_data.xml
odoo/addons/ssi_accountant_general_audit_ws_ra120/security/res_group_data.xml
odoo/addons/ssi_accountant_general_audit_ws_ra120/static/description/icon.png
odoo/addons/ssi_accountant_general_audit_ws_ra120/views/accountant_balance_diff_category_views.xml
odoo14_addon_ssi_accountant_general_audit_ws_ra120-14.0.1.6.2.dev1.dist-info/METADATA
odoo14_addon_ssi_accountant_general_audit_ws_ra120-14.0.1.6.2.dev1.dist-info/WHEEL
odoo14_addon_ssi_accountant_general_audit_ws_ra120-14.0.1.6.2.dev1.dist-info/top_level.txt
odoo14_addon_ssi_accountant_general_audit_ws_ra120-14.0.1.6.2.dev1.dist-info/RECORD
